{
    "archdesc": {
        "level": "collection",
        "accessrestrict": [
            {
                "id": "aspace_d1ebdb0cd4159da31c408874a409d44e",
                "head": {
                    "value": "Conditions Governing Access"
                },
                "p": [
                    {
                        "value": "Materials are open without restrictions."
                    }
                ]
            }
        ],
        "acqinfo": [
            {
                "id": "aspace_870ae6d0e940dcfa4c3c4558bc8ae607",
                "head": {
                    "value": "Immediate Source of Acquisition"
                },
                "p": [
                    {
                        "value": "Provenance unknown. The accession number associated with this collection is 1999.021."
                    }
                ]
            }
        ],
        "arrangement": [
            {
                "id": "aspace_28487480dd7ce6ec92e65ea4e63a63aa",
                "head": {
                    "value": "Arrangement"
                },
                "p": [
                    {
                        "value": "The collection is a single series.  Folders are arranged alphabetically (case folders alphabetized by last name of defendant; others by topic)."
                    }
                ]
            }
        ],
        "bioghist": [
            {
                "id": "aspace_7f46baef565e1a3330b4fdddf91b0163",
                "chronlist": {
                    "head": [
                        {
                            "value": "The following chronology provides a backdrop for the Board of Higher Education of the City of New York cases included within this collection:"
                        }
                    ],
                    "chronitem": [
                        {
                            "date": {
                                "value": "1939"
                            },
                            "eventgrp": [
                                {
                                    "event": [
                                        {
                                            "value": "The New York State Legislature enacted Section 12-a of the Civil Service Law which provided in substance that \"no person shall be appointed to or retained in the public service nor in any public educational institution who becomes a member of any organization which advocates the overthrow of government by force or violence, or by any unlawful means (L. 1939, Ch. 547).\""
                                        }
                                    ]
                                }
                            ],
                            "value": "\n          \n          \n        "
                        },
                        {
                            "date": {
                                "value": "March 29, 1940"
                            },
                            "eventgrp": [
                                {
                                    "event": [
                                        {
                                            "value": " The Senate and Assembly of NY State adopted a Joint Resolution authorizing an investigation of the public educational system of the State of NY by a Joint Legislative Committee of the Senate and the Assembly.  Thereafter the committee, referred to as the \"Rapp-Coudert Committee,\" undertook and proceeded with this investigation. The techniques pioneered by the committee generally involved private interrogations followed by public hearings."
                                        }
                                    ]
                                }
                            ],
                            "value": "\n          \n          \n        "
                        },
                        {
                            "date": {
                                "value": "January 20, 1941"
                            },
                            "eventgrp": [
                                {
                                    "event": [
                                        {
                                            "value": "The Board of Higher Education adopted a resolution which provided in part as follows:  \"Now, Therefore, Be It Resolved, that this Board direct all members of the staffs and all other employees under their jurisdiction to promptly obey all subpoenas issued by the Joint Legislative Committee, and to give such testimony and such other information as may be required by the Committee or any subcommittee thereof, and to otherwise cooperate with said Committee to the best of their ability...\""
                                        }
                                    ]
                                }
                            ],
                            "value": "\n          \n          \n        "
                        },
                        {
                            "date": {
                                "value": "March 1949"
                            },
                            "eventgrp": [
                                {
                                    "event": [
                                        {
                                            "value": "The Legislature enacted the \"Feinberg Law\" which had for its principal purpose the more effective enforcement of the provisions of Section 12-a  of the Civil Service Law (L. 149, Ch. 360, as amended by Laws 1953, Ch. 681.)"
                                        }
                                    ]
                                }
                            ],
                            "value": "\n          \n          \n        "
                        },
                        {
                            "date": {
                                "value": "July 15, 1949"
                            },
                            "eventgrp": [
                                {
                                    "event": [
                                        {
                                            "value": "Rules were promulgated by the Board of Regents under and in accordance with the Feinberg Law concerning a list to be maintained of organizations the Board found subversive."
                                        }
                                    ]
                                }
                            ],
                            "value": "\n          \n          \n        "
                        },
                        {
                            "date": {
                                "value": "March 3, 1952"
                            },
                            "eventgrp": [
                                {
                                    "event": [
                                        {
                                            "value": "In , the US Supreme Court upheld the Feinberg Law (\"The Court finds no constitutional infirmity in Section 12-a of the Civil Service Law of New ...\")"
                                        }
                                    ]
                                }
                            ],
                            "value": "\n          \n          \n        "
                        },
                        {
                            "date": {
                                "value": "June 15, 1953"
                            },
                            "eventgrp": [
                                {
                                    "event": [
                                        {
                                            "value": "A Special Committee of the Board of Higher Education was appointed on \"Section 903 of the City Charter, the Feinberg Law and Related Matters.\"  The purpose of the Special Committee was to undertake an investigative program designed to obtain all of the facts and available information relating to the membership and activities of any college staff members in or connected with subsersive organizations and particularly of the Communist Party, and to take or recommend such actions as the facts warrant."
                                        }
                                    ]
                                }
                            ],
                            "value": "\n          \n          \n        "
                        },
                        {
                            "date": {
                                "value": "September 28, 1953"
                            },
                            "eventgrp": [
                                {
                                    "event": [
                                        {
                                            "value": "The Board of Higher Education adopted a resolution authorizing the Board's Special Committee..., or a duly credited representative of the Special Committee, to call in for questioning such members of the staffs as the Special Committee or its representatives deemed necessary with respect to possible past or present membership or association with any organization that advocates or teaches the doctrine of the forceful overthrow of the Government of the United States or with respect to past or present participation in activities of any such organization by any staff members.  And further, that failure to cooperate fully and to answer all proper questions would subject staff members to disciplinary action."
                                        }
                                    ]
                                }
                            ],
                            "value": "\n          \n          \n        "
                        },
                        {
                            "date": {
                                "value": "January 23, 1967"
                            },
                            "eventgrp": [
                                {
                                    "event": [
                                        {
                                            "value": "By a vote of 5 to 4, the US Supreme Court, in , declared unconstitutional New York statutes and administrative rules designed to prevent employment of \"subversive\" teachers and professors in state educational institutions...The decision rejected a state's power to make public employment conditional on surrendering constitutional rights that could not otherwise be abridged by direct state action.      "
                                        }
                                    ]
                                }
                            ],
                            "value": "\n          \n          \n        "
                        }
                    ]
                },
                "head": {
                    "value": "Historical/Biographical Note"
                }
            }
        ],
        "controlaccess": {
            "corpname": [
                {
                    "value": "Teachers' Union of the City of New York"
                },
                {
                    "value": "New York (State). Legislature. Joint Legislative Committee to Investigate the Educational System of the State of New York"
                },
                {
                    "value": "City University of New York. City College"
                },
                {
                    "value": "Communist Party of the United States of America (New York)"
                }
            ],
            "genreform": [
                "Testimonies.",
                "Transcripts."
            ],
            "geogname": [
                "New York (N.Y.)."
            ],
            "persname": [
                {
                    "value": "McGill, V. J. (Vivian Jerauld), 1897-1977"
                },
                {
                    "value": "Weisner, Louis, 1899-"
                },
                {
                    "value": "Foner, Philip Sheldon, 1910-1994"
                }
            ],
            "subject": [
                "College teachers -- Political activity -- United States.",
                "Academic freedom |z New York (State) |z New York."
            ]
        },
        "did": {
            "physdesc": [
                {
                    "altrender": "whole",
                    "extent": [
                        {
                            "value": "2 Linear Feet",
                            "altrender": "materialtype spaceoccupied"
                        },
                        {
                            "value": " (2 boxes)",
                            "altrender": "carrier"
                        }
                    ]
                }
            ],
            "abstract": [
                {
                    "value": "This collection consists primarily of transcripts and testimony from hearings and investigations conducted by the State Board of Higher Education of the City of New York.  The materials focus on alleged Communist Party activities of eight faculty members at City College of New York, Hunter College and Queens College.",
                    "id": "aspace_164ede4f8271a5cc73f948899cb4cf46"
                }
            ],
            "langmaterial": [
                {
                    "value": "Materials are in English.",
                    "id": "aspace_b8c92904239bf6c39034f5618a1ce416"
                }
            ],
            "origination": [
                {
                    "label": "Creator",
                    "corpname": {
                        "value": "New York (N.Y.). Board of Education"
                    }
                }
            ],
            "repository": {
                "corpname": {
                    "value": "Tamiment Library and Robert F. Wagner Labor Archives"
                },
                "value": "\n        \n      "
            },
            "unitdate": [
                {
                    "type": "inclusive",
                    "value": "1941-1956"
                }
            ],
            "unitid": "TAM.332",
            "unittitle": {
                "value": "Board of Higher Education of the City of New York Academic Freedom Case Files"
            }
        },
        "dsc": {
            "c": [
                {
                    "id": "aspace_ref6",
                    "level": "file",
                    "did": {
                        "container": [
                            {
                                "barcode": "31142062758753",
                                "label": "Mixed Materials",
                                "altrender": "Record carton",
                                "id": "aspace_bb4aa56cd6ad7e218be156416f752e27",
                                "type": "box",
                                "value": "1"
                            },
                            {
                                "id": "aspace_7f204bdd7469f371745b91f910f451ff",
                                "parent": "aspace_bb4aa56cd6ad7e218be156416f752e27",
                                "type": "folder",
                                "value": "1"
                            }
                        ],
                        "unitdate": [
                            {
                                "type": "inclusive",
                                "value": "[1954]"
                            }
                        ],
                        "unittitle": {
                            "value": "Academic Freedom: \"The Loyalty Investigation of our Municipal Colleges\" (Board of Higher Education Policy Statement)"
                        }
                    }
                },
                {
                    "id": "aspace_ref7",
                    "level": "file",
                    "did": {
                        "container": [
                            {
                                "barcode": "31142062758753",
                                "label": "Mixed Materials",
                                "altrender": "Record carton",
                                "id": "aspace_7edfd11b7200b2e05b16905c5e302ac2",
                                "type": "box",
                                "value": "1"
                            },
                            {
                                "id": "aspace_35380576d052762dfffc01a155a5bfee",
                                "parent": "aspace_7edfd11b7200b2e05b16905c5e302ac2",
                                "type": "folder",
                                "value": "2"
                            }
                        ],
                        "unitdate": [
                            {
                                "type": "inclusive",
                                "value": "[1942]"
                            }
                        ],
                        "unittitle": {
                            "value": "Analysis and Appraisal of \u003cspan class=\"ead-emph ead-emph-italic\"\u003e The Report of the Rapp-Coudert Committee\u003c/span\u003e by the National Lawyers Guild"
                        }
                    }
                },
                {
                    "id": "aspace_ref8",
                    "level": "file",
                    "did": {
                        "container": [
                            {
                                "barcode": "31142062758753",
                                "label": "Mixed Materials",
                                "altrender": "Record carton",
                                "id": "aspace_545b3ac824d1f8b5140cc22b58b73334",
                                "type": "box",
                                "value": "1"
                            },
                            {
                                "id": "aspace_0600a1ddb6da2dc92cc47e95565c3c60",
                                "parent": "aspace_545b3ac824d1f8b5140cc22b58b73334",
                                "type": "folder",
                                "value": "3"
                            }
                        ],
                        "unitdate": [
                            {
                                "type": "inclusive",
                                "value": "Aug 25, 1941-Aug 27, 1941"
                            }
                        ],
                        "unittitle": {
                            "value": "Bernstein, Saul: \u003cspan class=\"ead-emph ead-emph-italic\"\u003eBoard of Higher Education of the City of New York v. Saul Bernstein\u003c/span\u003e, City College"
                        }
                    }
                },
                {
                    "id": "aspace_ref9",
                    "level": "file",
                    "did": {
                        "container": [
                            {
                                "barcode": "31142062758753",
                                "label": "Mixed Materials",
                                "altrender": "Record carton",
                                "id": "aspace_8a54f3d35b9641bc4635fcaf519e43bf",
                                "type": "box",
                                "value": "1"
                            },
                            {
                                "id": "aspace_4995a244785d71f5ddf686285ebe0c7e",
                                "parent": "aspace_8a54f3d35b9641bc4635fcaf519e43bf",
                                "type": "folder",
                                "value": "4"
                            }
                        ],
                        "unitdate": [
                            {
                                "type": "inclusive",
                                "value": "Jul 7, 1941"
                            }
                        ],
                        "unittitle": {
                            "value": "Braunlich, Arthur R., Jr.: \u003cspan class=\"ead-emph ead-emph-italic\"\u003eBoard of Higher Education of the City of New York v. Arthur R. Braunlich Jr.\u003c/span\u003e, City College"
                        }
                    }
                },
                {
                    "id": "aspace_ref10",
                    "level": "file",
                    "did": {
                        "container": [
                            {
                                "barcode": "31142062758753",
                                "label": "Mixed Materials",
                                "altrender": "Record carton",
                                "id": "aspace_883bb72bae8418b932a240170eead3b8",
                                "type": "box",
                                "value": "1"
                            },
                            {
                                "id": "aspace_c1fa5b7f4442bd862db24ad640847361",
                                "parent": "aspace_883bb72bae8418b932a240170eead3b8",
                                "type": "folder",
                                "value": "5"
                            }
                        ],
                        "unitdate": [
                            {
                                "type": "inclusive",
                                "value": "Jul 8, 1941"
                            }
                        ],
                        "unittitle": {
                            "value": "Braunlich, Arthur R., Jr.: \u003cspan class=\"ead-emph ead-emph-italic\"\u003eBoard of Higher Education of the City of New York v. Arthur R. Braunlich Jr.\u003c/span\u003e, City College"
                        }
                    }
                },
                {
                    "id": "aspace_ref11",
                    "level": "file",
                    "did": {
                        "container": [
                            {
                                "barcode": "31142062758753",
                                "label": "Mixed Materials",
                                "altrender": "Record carton",
                                "id": "aspace_ccc93915bda5abcffa708fdac8f663eb",
                                "type": "box",
                                "value": "1"
                            },
                            {
                                "id": "aspace_378d8b1d4fa94f2bca2aed474c04a134",
                                "parent": "aspace_ccc93915bda5abcffa708fdac8f663eb",
                                "type": "folder",
                                "value": "6"
                            }
                        ],
                        "unitdate": [
                            {
                                "type": "inclusive",
                                "value": "Jul 9, 1941"
                            }
                        ],
                        "unittitle": {
                            "value": "Braunlich, Arthur R., Jr.: \u003cspan class=\"ead-emph ead-emph-italic\"\u003eBoard of Higher Education of the City of New York v. Arthur R. Braunlich Jr.\u003c/span\u003e, City College"
                        }
                    }
                },
                {
                    "id": "aspace_ref12",
                    "level": "file",
                    "did": {
                        "container": [
                            {
                                "barcode": "31142062758753",
                                "label": "Mixed Materials",
                                "altrender": "Record carton",
                                "id": "aspace_ce7f0249848a9c823656d84de763e017",
                                "type": "box",
                                "value": "1"
                            },
                            {
                                "id": "aspace_fc1db690c8f6176d3cc5935883071f06",
                                "parent": "aspace_ce7f0249848a9c823656d84de763e017",
                                "type": "folder",
                                "value": "7"
                            }
                        ],
                        "unitdate": [
                            {
                                "type": "inclusive",
                                "value": "Jul 11, 1941"
                            }
                        ],
                        "unittitle": {
                            "value": "Copstein, Seymour A.: \u003cspan class=\"ead-emph ead-emph-italic\"\u003eBoard of Higher Education of the City of New York v. Seymour A. Copstein\u003c/span\u003e, City College"
                        }
                    }
                },
                {
                    "id": "aspace_ref13",
                    "level": "file",
                    "did": {
                        "container": [
                            {
                                "barcode": "31142062758753",
                                "label": "Mixed Materials",
                                "altrender": "Record carton",
                                "id": "aspace_36f3cb11b258f821856f56900129e70c",
                                "type": "box",
                                "value": "1"
                            },
                            {
                                "id": "aspace_61f5a4cd948a05753b06f2db5f38a331",
                                "parent": "aspace_36f3cb11b258f821856f56900129e70c",
                                "type": "folder",
                                "value": "8"
                            }
                        ],
                        "unitdate": [
                            {
                                "type": "inclusive",
                                "value": "Jul 14, 1941"
                            }
                        ],
                        "unittitle": {
                            "value": "Copstein, Seymour A.: \u003cspan class=\"ead-emph ead-emph-italic\"\u003eBoard of Higher Education of the City of New York v. Seymour A. Copstein\u003c/span\u003e, City College"
                        }
                    }
                },
                {
                    "id": "aspace_ref14",
                    "level": "file",
                    "did": {
                        "container": [
                            {
                                "barcode": "31142062758753",
                                "label": "Mixed Materials",
                                "altrender": "Record carton",
                                "id": "aspace_934026cedad44978090c4d0acc365060",
                                "type": "box",
                                "value": "1"
                            },
                            {
                                "id": "aspace_91e0cb7696ddfb3636c3583850ba0946",
                                "parent": "aspace_934026cedad44978090c4d0acc365060",
                                "type": "folder",
                                "value": "9"
                            }
                        ],
                        "unitdate": [
                            {
                                "type": "inclusive",
                                "value": "Jul 15, 1941"
                            }
                        ],
                        "unittitle": {
                            "value": "Copstein, Seymour A.: \u003cspan class=\"ead-emph ead-emph-italic\"\u003eBoard of Higher Education of the City of New York v. Seymour A. Copstein\u003c/span\u003e, City College"
                        }
                    }
                },
                {
                    "id": "aspace_ref15",
                    "level": "file",
                    "did": {
                        "container": [
                            {
                                "barcode": "31142062758753",
                                "label": "Mixed Materials",
                                "altrender": "Record carton",
                                "id": "aspace_ec39c82f1b3be9277fde2a54893a0e83",
                                "type": "box",
                                "value": "1"
                            },
                            {
                                "id": "aspace_9c522098f76f5cad05deddf8a4db4e2a",
                                "parent": "aspace_ec39c82f1b3be9277fde2a54893a0e83",
                                "type": "folder",
                                "value": "10"
                            }
                        ],
                        "unitdate": [
                            {
                                "type": "inclusive",
                                "value": "Aug 19, 1941"
                            }
                        ],
                        "unittitle": {
                            "value": "Foner, Philip S.: \u003cspan class=\"ead-emph ead-emph-italic\"\u003eBoard of Higher Education of the City of New York v. Philip S. Foner\u003c/span\u003e, City College"
                        }
                    }
                },
                {
                    "id": "aspace_ref16",
                    "level": "file",
                    "did": {
                        "container": [
                            {
                                "barcode": "31142062758753",
                                "label": "Mixed Materials",
                                "altrender": "Record carton",
                                "id": "aspace_9735e912c12cdb5575db1984e56b0ea5",
                                "type": "box",
                                "value": "1"
                            },
                            {
                                "id": "aspace_38f081e90a4c3a6aa3f8236d7d6460c0",
                                "parent": "aspace_9735e912c12cdb5575db1984e56b0ea5",
                                "type": "folder",
                                "value": "11"
                            }
                        ],
                        "unitdate": [
                            {
                                "type": "inclusive",
                                "value": "Aug 20, 1941"
                            }
                        ],
                        "unittitle": {
                            "value": "Foner, Philip S.: \u003cspan class=\"ead-emph ead-emph-italic\"\u003eBoard of Higher Education of the City of New York v. Philip S. Foner\u003c/span\u003e, City College  (I)"
                        }
                    }
                },
                {
                    "id": "aspace_ref17",
                    "level": "file",
                    "did": {
                        "container": [
                            {
                                "barcode": "31142062758753",
                                "label": "Mixed Materials",
                                "altrender": "Record carton",
                                "id": "aspace_94fc8a69f5489549122d70d821624ec7",
                                "type": "box",
                                "value": "1"
                            },
                            {
                                "id": "aspace_b87fe1c7133c76afc9c87821bd40244d",
                                "parent": "aspace_94fc8a69f5489549122d70d821624ec7",
                                "type": "folder",
                                "value": "12"
                            }
                        ],
                        "unitdate": [
                            {
                                "type": "inclusive",
                                "value": "Aug 20, 1941"
                            }
                        ],
                        "unittitle": {
                            "value": "Foner, Philip S.: \u003cspan class=\"ead-emph ead-emph-italic\"\u003eBoard of Higher Education of the City of New York v. Philip S. Foner\u003c/span\u003e, City College  (II)"
                        }
                    }
                },
                {
                    "id": "aspace_ref18",
                    "level": "file",
                    "did": {
                        "container": [
                            {
                                "barcode": "31142062758753",
                                "label": "Mixed Materials",
                                "altrender": "Record carton",
                                "id": "aspace_b592e16c0d01c8ea828db79a55d87670",
                                "type": "box",
                                "value": "1"
                            },
                            {
                                "id": "aspace_db433e06f73e843eb59e636a93f1fdb4",
                                "parent": "aspace_b592e16c0d01c8ea828db79a55d87670",
                                "type": "folder",
                                "value": "13"
                            }
                        ],
                        "unitdate": [
                            {
                                "type": "inclusive",
                                "value": "Jun 1, 1954"
                            }
                        ],
                        "unittitle": {
                            "value": "Hughes, Charles W.: \u003cspan class=\"ead-emph ead-emph-italic\"\u003eBoard of Higher Education of the City of New York v. Charles W. Hughes\u003c/span\u003e, Hunter College  (I)"
                        }
                    }
                },
                {
                    "id": "aspace_ref19",
                    "level": "file",
                    "did": {
                        "container": [
                            {
                                "barcode": "31142062758753",
                                "label": "Mixed Materials",
                                "altrender": "Record carton",
                                "id": "aspace_74182dbdd09026e383c09d15d4923435",
                                "type": "box",
                                "value": "1"
                            },
                            {
                                "id": "aspace_38d58353c8c8730b042462047e7a740e",
                                "parent": "aspace_74182dbdd09026e383c09d15d4923435",
                                "type": "folder",
                                "value": "14"
                            }
                        ],
                        "unitdate": [
                            {
                                "type": "inclusive",
                                "value": "Jun 1, 1954"
                            }
                        ],
                        "unittitle": {
                            "value": "Hughes, Charles W.: \u003cspan class=\"ead-emph ead-emph-italic\"\u003eBoard of Higher Education of the City of New York v. Charles W. Hughes\u003c/span\u003e, Hunter College  (II)"
                        }
                    }
                },
                {
                    "id": "aspace_ref20",
                    "level": "file",
                    "did": {
                        "container": [
                            {
                                "barcode": "31142062758753",
                                "label": "Mixed Materials",
                                "altrender": "Record carton",
                                "id": "aspace_bdc5eb8e40a84b70696533b26c2ba7ea",
                                "type": "box",
                                "value": "1"
                            },
                            {
                                "id": "aspace_dc55a2077daf95facfd8af1278dd125c",
                                "parent": "aspace_bdc5eb8e40a84b70696533b26c2ba7ea",
                                "type": "folder",
                                "value": "15"
                            }
                        ],
                        "unitdate": [
                            {
                                "type": "inclusive",
                                "value": "Jun 1, 1954"
                            }
                        ],
                        "unittitle": {
                            "value": "Hughes, Charles W.: \u003cspan class=\"ead-emph ead-emph-italic\"\u003eBoard of Higher Education of the City of New York v. Charles W. Hughes\u003c/span\u003e, Hunter College  (III)"
                        }
                    }
                },
                {
                    "id": "aspace_ref21",
                    "level": "file",
                    "did": {
                        "container": [
                            {
                                "barcode": "31142062758753",
                                "label": "Mixed Materials",
                                "altrender": "Record carton",
                                "id": "aspace_127b0f503bd35456aa478f2c8aaa3124",
                                "type": "box",
                                "value": "1"
                            },
                            {
                                "id": "aspace_73fa2b22ec8b120aa5ff31b4b0820f4d",
                                "parent": "aspace_127b0f503bd35456aa478f2c8aaa3124",
                                "type": "folder",
                                "value": "16"
                            }
                        ],
                        "unitdate": [
                            {
                                "type": "inclusive",
                                "value": "Nov 20, 1953; Jan 29, 1954"
                            }
                        ],
                        "unittitle": {
                            "value": "McGill, V. Jerauld: \u003cspan class=\"ead-emph ead-emph-italic\"\u003eBoard of Higher Education of the City of New York v. V. Jerauld McGill\u003c/span\u003e, Hunter College - Testimony before Special Committee"
                        }
                    }
                },
                {
                    "id": "aspace_ref22",
                    "level": "file",
                    "did": {
                        "container": [
                            {
                                "barcode": "31142062758753",
                                "label": "Mixed Materials",
                                "altrender": "Record carton",
                                "id": "aspace_66f75852381ea10251237467ab3989fa",
                                "type": "box",
                                "value": "1"
                            },
                            {
                                "id": "aspace_487a565fd8529c6ccd2cf1be8b8994c4",
                                "parent": "aspace_66f75852381ea10251237467ab3989fa",
                                "type": "folder",
                                "value": "17"
                            }
                        ],
                        "unitdate": [
                            {
                                "type": "inclusive",
                                "value": "Mar 12, 1954"
                            }
                        ],
                        "unittitle": {
                            "value": "McGill, V. Jerauld: \u003cspan class=\"ead-emph ead-emph-italic\"\u003eBoard of Higher Education of the City of New York v. V. Jerauld McGill\u003c/span\u003e, Hunter College - Testimony before Special Counsel"
                        }
                    }
                },
                {
                    "id": "aspace_ref23",
                    "level": "file",
                    "did": {
                        "container": [
                            {
                                "barcode": "31142062758753",
                                "label": "Mixed Materials",
                                "altrender": "Record carton",
                                "id": "aspace_345fae85d21a4ec9b889696d6a6d543e",
                                "type": "box",
                                "value": "1"
                            },
                            {
                                "id": "aspace_533f42d4b1bb9d02b52f12ade4df9666",
                                "parent": "aspace_345fae85d21a4ec9b889696d6a6d543e",
                                "type": "folder",
                                "value": "18"
                            }
                        ],
                        "unitdate": [
                            {
                                "type": "inclusive",
                                "value": "Mar 30, 1954"
                            }
                        ],
                        "unittitle": {
                            "value": "McGill, V. Jerauld: \u003cspan class=\"ead-emph ead-emph-italic\"\u003eBoard of Higher Education of the City of New York v. V. Jerauld McGill\u003c/span\u003e, Hunter College - Testimony before Special Committee"
                        }
                    }
                },
                {
                    "id": "aspace_ref24",
                    "level": "file",
                    "did": {
                        "container": [
                            {
                                "barcode": "31142062758753",
                                "label": "Mixed Materials",
                                "altrender": "Record carton",
                                "id": "aspace_eb029160eeeb72ff326534147c22653e",
                                "type": "box",
                                "value": "1"
                            },
                            {
                                "id": "aspace_cb65673b2035d206a88aee99c78013c2",
                                "parent": "aspace_eb029160eeeb72ff326534147c22653e",
                                "type": "folder",
                                "value": "19"
                            }
                        ],
                        "unitdate": [
                            {
                                "type": "inclusive",
                                "value": "Apr 8, 1954"
                            }
                        ],
                        "unittitle": {
                            "value": "McGill, V. Jerauld: \u003cspan class=\"ead-emph ead-emph-italic\"\u003eBoard of Higher Education of the City of New York v. V. Jerauld McGill\u003c/span\u003e, Hunter College - Testimony before Special Committee"
                        }
                    }
                },
                {
                    "id": "aspace_ref25",
                    "level": "file",
                    "did": {
                        "container": [
                            {
                                "barcode": "31142062758753",
                                "label": "Mixed Materials",
                                "altrender": "Record carton",
                                "id": "aspace_0236e913e66f7b787e5e7f3d312d350d",
                                "type": "box",
                                "value": "1"
                            },
                            {
                                "id": "aspace_b4ffecb6cbedc05599dedd795dad8443",
                                "parent": "aspace_0236e913e66f7b787e5e7f3d312d350d",
                                "type": "folder",
                                "value": "20"
                            }
                        ],
                        "unitdate": [
                            {
                                "type": "inclusive",
                                "value": "May 27, 1954"
                            }
                        ],
                        "unittitle": {
                            "value": "McGill, V. Jerauld: \u003cspan class=\"ead-emph ead-emph-italic\"\u003eBoard of Higher Education of the City of New York v. V. Jerauld McGill\u003c/span\u003e, Hunter College   (I)"
                        }
                    }
                },
                {
                    "id": "aspace_ref26",
                    "level": "file",
                    "did": {
                        "container": [
                            {
                                "barcode": "31142062758761",
                                "label": "Mixed Materials",
                                "altrender": "Record carton",
                                "id": "aspace_0492b2260402b77855bbc1ae8f96074d",
                                "type": "box",
                                "value": "2"
                            },
                            {
                                "id": "aspace_ae702c5d8796ad9461daca6168d5f3c8",
                                "parent": "aspace_0492b2260402b77855bbc1ae8f96074d",
                                "type": "folder",
                                "value": "1"
                            }
                        ],
                        "unitdate": [
                            {
                                "type": "inclusive",
                                "value": "May 27, 1954"
                            }
                        ],
                        "unittitle": {
                            "value": "McGill, V. Jerauld: \u003cspan class=\"ead-emph ead-emph-italic\"\u003eBoard of Higher Education of the City of New York v. V. Jerauld McGill\u003c/span\u003e, Hunter College  (II)"
                        }
                    }
                },
                {
                    "id": "aspace_ref27",
                    "level": "file",
                    "did": {
                        "container": [
                            {
                                "barcode": "31142062758761",
                                "label": "Mixed Materials",
                                "altrender": "Record carton",
                                "id": "aspace_94941446b3b47fb6de9bd7b1e30df460",
                                "type": "box",
                                "value": "2"
                            },
                            {
                                "id": "aspace_5f56ab45a7a33b382d05787ac794736d",
                                "parent": "aspace_94941446b3b47fb6de9bd7b1e30df460",
                                "type": "folder",
                                "value": "2"
                            }
                        ],
                        "unitdate": [
                            {
                                "type": "inclusive",
                                "value": "May 27, 1954"
                            }
                        ],
                        "unittitle": {
                            "value": "McGill, V. Jerauld: \u003cspan class=\"ead-emph ead-emph-italic\"\u003eBoard of Higher Education of the City of New York v. V. Jerauld McGill\u003c/span\u003e, Hunter College  (III)"
                        }
                    }
                },
                {
                    "id": "aspace_ref28",
                    "level": "file",
                    "did": {
                        "container": [
                            {
                                "barcode": "31142062758761",
                                "label": "Mixed Materials",
                                "altrender": "Record carton",
                                "id": "aspace_1a0c3c665bfd4e56d4914e95d9f2e348",
                                "type": "box",
                                "value": "2"
                            },
                            {
                                "id": "aspace_edbbf5ba78fe7cf9edc3c341c960e75a",
                                "parent": "aspace_1a0c3c665bfd4e56d4914e95d9f2e348",
                                "type": "folder",
                                "value": "3"
                            }
                        ],
                        "unitdate": [
                            {
                                "type": "inclusive",
                                "value": "Jun 8, 1954"
                            }
                        ],
                        "unittitle": {
                            "value": "McGill, V. Jerauld: \u003cspan class=\"ead-emph ead-emph-italic\"\u003eBoard of Higher Education of the City of New York v. V. Jerauld McGill\u003c/span\u003e, Hunter College  "
                        }
                    }
                },
                {
                    "id": "aspace_ref29",
                    "level": "file",
                    "did": {
                        "container": [
                            {
                                "barcode": "31142062758761",
                                "label": "Mixed Materials",
                                "altrender": "Record carton",
                                "id": "aspace_1a34709d675475a7cfff56ab346f9914",
                                "type": "box",
                                "value": "2"
                            },
                            {
                                "id": "aspace_b57279e7da5680e1f3ebe14fce28caf0",
                                "parent": "aspace_1a34709d675475a7cfff56ab346f9914",
                                "type": "folder",
                                "value": "4"
                            }
                        ],
                        "unitdate": [
                            {
                                "type": "inclusive",
                                "value": "Jun 9, 1954"
                            }
                        ],
                        "unittitle": {
                            "value": "McGill, V. Jerauld: \u003cspan class=\"ead-emph ead-emph-italic\"\u003eBoard of Higher Education of the City of New York v. V. Jerauld McGill\u003c/span\u003e, Hunter College  "
                        }
                    }
                },
                {
                    "id": "aspace_ref30",
                    "level": "file",
                    "did": {
                        "container": [
                            {
                                "barcode": "31142062758761",
                                "label": "Mixed Materials",
                                "altrender": "Record carton",
                                "id": "aspace_68b41dd0ed5628ff8587872b93d71690",
                                "type": "box",
                                "value": "2"
                            },
                            {
                                "id": "aspace_8b641ebb2b76760e2099d09c62f24ac9",
                                "parent": "aspace_68b41dd0ed5628ff8587872b93d71690",
                                "type": "folder",
                                "value": "5"
                            }
                        ],
                        "unitdate": [
                            {
                                "type": "inclusive",
                                "value": "Jun 15, 1954"
                            }
                        ],
                        "unittitle": {
                            "value": "McGill, V. Jerauld: \u003cspan class=\"ead-emph ead-emph-italic\"\u003eBoard of Higher Education of the City of New York v. V. Jerauld McGill\u003c/span\u003e, Hunter College  "
                        }
                    }
                },
                {
                    "id": "aspace_ref31",
                    "level": "file",
                    "did": {
                        "container": [
                            {
                                "barcode": "31142062758761",
                                "label": "Mixed Materials",
                                "altrender": "Record carton",
                                "id": "aspace_d722784c1739bea440a74e5482548c39",
                                "type": "box",
                                "value": "2"
                            },
                            {
                                "id": "aspace_c9b46871f4e1d9559f75cc5481b28594",
                                "parent": "aspace_d722784c1739bea440a74e5482548c39",
                                "type": "folder",
                                "value": "6"
                            }
                        ],
                        "unitdate": [
                            {
                                "type": "inclusive",
                                "value": "Jun 17, 1954"
                            }
                        ],
                        "unittitle": {
                            "value": "McGill, V. Jerauld: \u003cspan class=\"ead-emph ead-emph-italic\"\u003eBoard of Higher Education of the City of New York v. V. Jerauld McGill\u003c/span\u003e, Hunter College  "
                        }
                    }
                },
                {
                    "id": "aspace_ref32",
                    "level": "file",
                    "did": {
                        "container": [
                            {
                                "barcode": "31142062758761",
                                "label": "Mixed Materials",
                                "altrender": "Record carton",
                                "id": "aspace_1e2b5eb389c241dffa3f938a7a3065d2",
                                "type": "box",
                                "value": "2"
                            },
                            {
                                "id": "aspace_b485a64a1038b5d32e6740638d41aa67",
                                "parent": "aspace_1e2b5eb389c241dffa3f938a7a3065d2",
                                "type": "folder",
                                "value": "7"
                            }
                        ],
                        "unitdate": [
                            {
                                "type": "inclusive",
                                "value": "Jul 6, 1954"
                            }
                        ],
                        "unittitle": {
                            "value": "McGill, V. Jerauld: \u003cspan class=\"ead-emph ead-emph-italic\"\u003eBoard of Higher Education of the City of New York v. V. Jerauld McGill\u003c/span\u003e, Hunter College  "
                        }
                    }
                },
                {
                    "id": "aspace_ref33",
                    "level": "file",
                    "did": {
                        "container": [
                            {
                                "barcode": "31142062758761",
                                "label": "Mixed Materials",
                                "altrender": "Record carton",
                                "id": "aspace_83046c2803121bbff107890d48ec2a0a",
                                "type": "box",
                                "value": "2"
                            },
                            {
                                "id": "aspace_6dc70409ff60e99dd0e580532ce9477f",
                                "parent": "aspace_83046c2803121bbff107890d48ec2a0a",
                                "type": "folder",
                                "value": "8"
                            }
                        ],
                        "unitdate": [
                            {
                                "type": "inclusive",
                                "value": "Jul 15, 1954"
                            }
                        ],
                        "unittitle": {
                            "value": "McGill, V. Jerauld: \u003cspan class=\"ead-emph ead-emph-italic\"\u003eBoard of Higher Education of the City of New York v. V. Jerauld McGill\u003c/span\u003e, Hunter College  "
                        }
                    }
                },
                {
                    "id": "aspace_ref34",
                    "level": "file",
                    "did": {
                        "container": [
                            {
                                "barcode": "31142062758761",
                                "label": "Mixed Materials",
                                "altrender": "Record carton",
                                "id": "aspace_8c4fef66cacaf8bccfe160112fc0c5d6",
                                "type": "box",
                                "value": "2"
                            },
                            {
                                "id": "aspace_e9e255bb84b24aa48a28692de9c5faff",
                                "parent": "aspace_8c4fef66cacaf8bccfe160112fc0c5d6",
                                "type": "folder",
                                "value": "9"
                            }
                        ],
                        "unitdate": [
                            {
                                "type": "inclusive",
                                "value": "Jul 23, 1954"
                            }
                        ],
                        "unittitle": {
                            "value": "McGill, V. Jerauld: \u003cspan class=\"ead-emph ead-emph-italic\"\u003eBoard of Higher Education of the City of New York v. V. Jerauld McGill\u003c/span\u003e, Hunter College  "
                        }
                    }
                },
                {
                    "id": "aspace_ref35",
                    "level": "file",
                    "did": {
                        "container": [
                            {
                                "barcode": "31142062758761",
                                "label": "Mixed Materials",
                                "altrender": "Record carton",
                                "id": "aspace_99040c355ac130a5e34712a33c14a3b3",
                                "type": "box",
                                "value": "2"
                            },
                            {
                                "id": "aspace_edceca5fe712e351d23bb8e954f56f35",
                                "parent": "aspace_99040c355ac130a5e34712a33c14a3b3",
                                "type": "folder",
                                "value": "10"
                            }
                        ],
                        "unitdate": [
                            {
                                "type": "inclusive",
                                "value": "Sep 17, 1954"
                            }
                        ],
                        "unittitle": {
                            "value": "McGill, V. Jerauld: \u003cspan class=\"ead-emph ead-emph-italic\"\u003eBoard of Higher Education of the City of New York v. V. Jerauld McGill, Louis Weisner and Charles W. Hughes\u003c/span\u003e, Hunter College - Report of the Trial Committee"
                        }
                    }
                },
                {
                    "id": "aspace_ref36",
                    "level": "file",
                    "did": {
                        "container": [
                            {
                                "barcode": "31142062758761",
                                "label": "Mixed Materials",
                                "altrender": "Record carton",
                                "id": "aspace_5ab9bed983bcd3294aa7bfc443d50d11",
                                "type": "box",
                                "value": "2"
                            },
                            {
                                "id": "aspace_6e8b825cce99c4f15860b8bcc08b536f",
                                "parent": "aspace_5ab9bed983bcd3294aa7bfc443d50d11",
                                "type": "folder",
                                "value": "11"
                            }
                        ],
                        "unitdate": [
                            {
                                "type": "inclusive",
                                "value": "Mar 25, 1955"
                            }
                        ],
                        "unittitle": {
                            "value": "Straus, Dudley David: \u003cspan class=\"ead-emph ead-emph-italic\"\u003eBoard of Higher Education of the City of New York v. Dudley David Straus\u003c/span\u003e, Queens College"
                        }
                    }
                },
                {
                    "id": "aspace_ref37",
                    "level": "file",
                    "did": {
                        "container": [
                            {
                                "barcode": "31142062758761",
                                "label": "Mixed Materials",
                                "altrender": "Record carton",
                                "id": "aspace_f43d966d0055e01739946f1f8f51c806",
                                "type": "box",
                                "value": "2"
                            },
                            {
                                "id": "aspace_df7c8e36b4c605efde526d58977fd9b0",
                                "parent": "aspace_f43d966d0055e01739946f1f8f51c806",
                                "type": "folder",
                                "value": "12"
                            }
                        ],
                        "unitdate": [
                            {
                                "type": "inclusive",
                                "value": "Mar 31, 1955"
                            }
                        ],
                        "unittitle": {
                            "value": "Straus, Dudley David: \u003cspan class=\"ead-emph ead-emph-italic\"\u003eBoard of Higher Education of the City of New York v. Dudley David Straus\u003c/span\u003e, Queens College"
                        }
                    }
                },
                {
                    "id": "aspace_ref38",
                    "level": "file",
                    "did": {
                        "container": [
                            {
                                "barcode": "31142062758761",
                                "label": "Mixed Materials",
                                "altrender": "Record carton",
                                "id": "aspace_34236df2a3dd6afc016d5a2877075acb",
                                "type": "box",
                                "value": "2"
                            },
                            {
                                "id": "aspace_72773d9415606e71a5b92641e673bb0b",
                                "parent": "aspace_34236df2a3dd6afc016d5a2877075acb",
                                "type": "folder",
                                "value": "13"
                            }
                        ],
                        "unitdate": [
                            {
                                "type": "inclusive",
                                "value": "Mar 26, 1954"
                            }
                        ],
                        "unittitle": {
                            "value": "Weisner, Louis: \u003cspan class=\"ead-emph ead-emph-italic\"\u003eBoard of Higher Education of the City of New York v. Louis Weisner\u003c/span\u003e, Hunter College - Testimony before Special Committee"
                        }
                    }
                },
                {
                    "id": "aspace_ref39",
                    "level": "file",
                    "did": {
                        "container": [
                            {
                                "barcode": "31142062758761",
                                "label": "Mixed Materials",
                                "altrender": "Record carton",
                                "id": "aspace_ae2a5eb124c39f1c77efb2ae50e77a20",
                                "type": "box",
                                "value": "2"
                            },
                            {
                                "id": "aspace_df8e2a27429c222a284cce7d4fffca3e",
                                "parent": "aspace_ae2a5eb124c39f1c77efb2ae50e77a20",
                                "type": "folder",
                                "value": "14"
                            }
                        ],
                        "unitdate": [
                            {
                                "type": "inclusive",
                                "value": "Jun 1, 1954"
                            }
                        ],
                        "unittitle": {
                            "value": "Weisner, Louis: \u003cspan class=\"ead-emph ead-emph-italic\"\u003eBoard of Higher Education of the City of New York v. Louis Weisner\u003c/span\u003e, Hunter College  (I)"
                        }
                    }
                },
                {
                    "id": "aspace_ref40",
                    "level": "file",
                    "did": {
                        "container": [
                            {
                                "barcode": "31142062758761",
                                "label": "Mixed Materials",
                                "altrender": "Record carton",
                                "id": "aspace_8b2277537e17a99b0ec86d9b81e14453",
                                "type": "box",
                                "value": "2"
                            },
                            {
                                "id": "aspace_9b8a21d929e2722d31a6ac116635c6f7",
                                "parent": "aspace_8b2277537e17a99b0ec86d9b81e14453",
                                "type": "folder",
                                "value": "15"
                            }
                        ],
                        "unitdate": [
                            {
                                "type": "inclusive",
                                "value": "Jun 1, 1954"
                            }
                        ],
                        "unittitle": {
                            "value": "Weisner, Louis: \u003cspan class=\"ead-emph ead-emph-italic\"\u003eBoard of Higher Education of the City of New York v. Louis Weisner\u003c/span\u003e, Hunter College  (II)"
                        }
                    }
                },
                {
                    "id": "aspace_ref41",
                    "level": "file",
                    "did": {
                        "container": [
                            {
                                "barcode": "31142062758761",
                                "label": "Mixed Materials",
                                "altrender": "Record carton",
                                "id": "aspace_bc44f135b5a17406512c8ccc8d917c7b",
                                "type": "box",
                                "value": "2"
                            },
                            {
                                "id": "aspace_981afe9cc93d3171cf4fcf12753f6488",
                                "parent": "aspace_bc44f135b5a17406512c8ccc8d917c7b",
                                "type": "folder",
                                "value": "16"
                            }
                        ],
                        "unitdate": [
                            {
                                "type": "inclusive",
                                "value": "Dec 11, 1956"
                            }
                        ],
                        "unittitle": {
                            "value": "Related Material: \u003cspan class=\"ead-emph ead-emph-italic\"\u003eBoard of Education of the City of New York and William Jansen v. James E. Allen, Jr., Harry Adler, Julius Nash, Minerva Feinstein, Irving Mauer and Samuel S. Cohen\u003c/span\u003e - Petitioners' Memorandum"
                        }
                    }
                },
                {
                    "id": "aspace_ref42",
                    "level": "file",
                    "did": {
                        "container": [
                            {
                                "barcode": "31142062758761",
                                "label": "Mixed Materials",
                                "altrender": "Record carton",
                                "id": "aspace_ff3416f1c06fada82270112c420e2c39",
                                "type": "box",
                                "value": "2"
                            },
                            {
                                "id": "aspace_f7c4b324368ecf8b38fb803a83ccdbb6",
                                "parent": "aspace_ff3416f1c06fada82270112c420e2c39",
                                "type": "folder",
                                "value": "17"
                            }
                        ],
                        "unitdate": [
                            {
                                "type": "inclusive",
                                "value": "Dec 11, 1950"
                            }
                        ],
                        "unittitle": {
                            "value": "Related Material: \u003cspan class=\"ead-emph ead-emph-italic\"\u003eBoard of Education of the City of New York and William Jansen v. Mark Friedlander\u003c/span\u003e - Trial Examiner Report"
                        }
                    }
                },
                {
                    "id": "aspace_ref43",
                    "level": "file",
                    "did": {
                        "container": [
                            {
                                "barcode": "31142062758761",
                                "label": "Mixed Materials",
                                "altrender": "Record carton",
                                "id": "aspace_2b69e310aab0cd537df7b9e9ed0f0379",
                                "type": "box",
                                "value": "2"
                            },
                            {
                                "id": "aspace_99cb53c649266444dfff39c9f3fc8017",
                                "parent": "aspace_2b69e310aab0cd537df7b9e9ed0f0379",
                                "type": "folder",
                                "value": "18"
                            }
                        ],
                        "unitdate": [
                            {
                                "type": "inclusive",
                                "value": "Dec 11, 1950 - Dec 12, 1950"
                            }
                        ],
                        "unittitle": {
                            "value": "Related Material: \u003cspan class=\"ead-emph ead-emph-italic\"\u003eBoard of Education of the City of New York and William Jansen v. David L. Friedman\u003c/span\u003e - Trial Examiner Report"
                        }
                    }
                },
                {
                    "id": "aspace_ref44",
                    "level": "file",
                    "did": {
                        "container": [
                            {
                                "barcode": "31142062758761",
                                "label": "Mixed Materials",
                                "altrender": "Record carton",
                                "id": "aspace_e784373ac811bf02c18f405fe0737d84",
                                "type": "box",
                                "value": "2"
                            },
                            {
                                "id": "aspace_cacfe6ce568367a52891e078d42e3e22",
                                "parent": "aspace_e784373ac811bf02c18f405fe0737d84",
                                "type": "folder",
                                "value": "19"
                            }
                        ],
                        "unitdate": [
                            {
                                "type": "inclusive",
                                "value": "[1949]"
                            }
                        ],
                        "unittitle": {
                            "value": "Related Material: Smith Act Trial - Defense Attorneys' Critique re: Judicial Conduct of Judge Harold R. Medina"
                        }
                    }
                }
            ]
        },
        "prefercite": [
            {
                "id": "aspace_6a43d4b23e8ace5cf0979fccea11031d",
                "head": {
                    "value": "Preferred Citation"
                },
                "p": [
                    {
                        "value": "Published citations should take the following form: \u003cbr\u003e\u003cbr\u003eIdentification of item, date; Collection name; Collection number; box number; folder number; \u003cbr\u003eTamiment Library/Robert F. Wagner Labor Archives \u003cbr\u003eElmer Holmes Bobst Library \u003cbr\u003e70 Washington Square South \u003cbr\u003eNew York, NY 10012, New York University Libraries."
                    }
                ]
            }
        ],
        "relatedmaterial": [
            {
                "id": "aspace_7c0222bab0d6abe1b20d8c666e1585ce",
                "head": {
                    "value": "Related Material at the Tamiment Library/Robert F. Wagner Labor Archives"
                },
                "p": [
                    {
                        "value": "Sidney Eisenberger Autobiographical Manuscript (TAM 370)"
                    },
                    {
                        "value": "Frederic Ewen Papers  (TAM 254)"
                    },
                    {
                        "value": "Frederic Ewen Audiotape and Videotape Collection   (TAM 277)"
                    },
                    {
                        "value": "Henry Foner Papers   (TAM 254)"
                    },
                    {
                        "value": "Rabinowitz, Boudin, Standard, Krinsky and Lieberman Legal Files  (TAM 287)"
                    }
                ]
            }
        ],
        "scopecontent": [
            {
                "id": "aspace_7c3f790472c2b783b418d891e2b03ce9",
                "head": {
                    "value": "Scope and Content Note"
                },
                "p": [
                    {
                        "value": "This collection is composed primarily of transcripts and testimonies from hearings and investigations concerning the alleged Communist Party membership or associations of eight faculty members of New York City public universities. Conducted by the Board of Higher Education of the City of New York, or its representatives, the hearings were held during two time periods: 1941 and 1953-1955. "
                    },
                    {
                        "value": "Hearings held in 1941 involved four members of the faculty of the City College of New York:  Saul Bernstein, Biology instructor; Arthur R. Braunlich, Jr., tutor of English; Seymour A. Copstein, also an English tutor; and Philip S. Foner, History instructor.  Each had previously appeared before the Joint Legislative Committee on the State Education System (Rapp-Coudert Committee) and each was charged with Party membership, committing perjury before Rapp-Coudert and failure to fully cooperate with the investigations."
                    },
                    {
                        "value": "The second group of transcripts and testimonies (1953-1955) involve four more faculty members:  Charles W. Hughes, associate professor in the Department of Music at Hunter College; V. Jerauld McGill, associate professor in the Department of Psychology and Philosophy at Hunter; Louis Weisner, associate professor of Mathematics at Hunter; and Dudley David Straus, English instructor at Queens College.  McGill had previously appeared before Rapp-Coudert and was charged with giving false testimony, witholding information from the Board's Special Committee and colluding with Charles Hughes and Louis Weisner to refuse to answer certain questions; i.e., to inform on others.  Hughes and Weisner were accused similarly (with the exception of the Rapp-Coudert perjury charge).  Dudley David Straus was also charged with Communist Party membership."
                    },
                    {
                        "value": "In addition to the transcripts and testimonies, there are a number of related documents including a copy of the Board's policy statement, \"The Loyalty Investigation of our Municipal Colleges\"; court documents from several related cases involving city secondary school teachers; an analysis and appraisal of The Report of the Rapp-Coudert Committee by the New York City Chapter of the National Lawyers Guild; and a critique of the judicial conduct of Judge Harold R. Medina in the 1949 Smith Act trial of Eugene Dennis and others."
                    }
                ]
            }
        ],
        "userestrict": [
            {
                "id": "aspace_3c52061d6809b6ba61a2f7d0271b2b87",
                "head": {
                    "value": "Conditions Governing Use"
                },
                "p": [
                    {
                        "value": "Materials in this collection, which were created by the Board of Higher Education of the City of New York in 1941-1956, are in the public domain. Users need not secure permission from the Tamiment library to publish or reproduce these materials. Copyright (and related rights to publicity and privacy) to the report of the Rapp-Coudert Committee created by the National Lawyers Guild was not transferred to New York University. Permission to use materials must be secured from the copyright holder."
                    }
                ]
            }
        ]
    },
    "eadheader": {
        "eadid": {
            "url": "http://dlib.nyu.edu/findingaids/html/tamwag/tam_332/",
            "value": "tam_332"
        },
        "filedesc": {
            "publicationstmt": {
                "address": {
                    "addressline": [
                        {
                            "value": "Elmer Holmes Bobst Library"
                        },
                        {
                            "value": "70 Washington Square South"
                        },
                        {
                            "value": "2nd Floor"
                        },
                        {
                            "value": "New York, NY 10012"
                        },
                        {
                            "value": "special.collections@nyu.edu"
                        },
                        {
                            "extptr": [
                                {
                                    "href": "http://library.nyu.edu/about/collections/special-collections-and-archives/special-collections/",
                                    "show": "new",
                                    "title": "http://library.nyu.edu/about/collections/special-collections-and-archives/special-collections/",
                                    "type": "simple"
                                }
                            ],
                            "value": "URL: "
                        }
                    ]
                },
                "p": [
                    {
                        "value": "\n          \u003cspan class=\"ead-date\"\u003e08/04/09\u003c/span\u003e\n        ",
                        "date": [
                            {
                                "value": "08/04/09"
                            }
                        ]
                    }
                ],
                "publisher": "Tamiment Library and Robert F. Wagner Labor Archives"
            },
            "titlestmt": {
                "author": "Jan Hilley",
                "titleproper": [
                    {
                        "value": "Guide to the Board of Higher Education of the City of New York Academic Freedom Case Files \u003cspan class=\"ead-num\"\u003eTAM.332\u003c/span\u003e",
                        "num": [
                            {
                                "value": "TAM.332"
                            }
                        ]
                    }
                ]
            }
        },
        "profiledesc": {
            "creation": {
                "date": {
                    "value": "2021-01-21 15:51:42 -0500"
                },
                "value": "This finding aid was produced using ArchivesSpace on ."
            },
            "descrules": "Describing Archives: A Content Standard",
            "langusage": {}
        }
    }
}